meggie_difference/__init__.py
meggie_difference/configuration.json
meggie_difference/actions/__init__.py
meggie_difference/actions/evoked_difference/__init__.py
meggie_difference/actions/evoked_difference/configuration.json
meggie_difference/actions/evoked_difference/tests/__init__.py
meggie_difference/actions/evoked_difference/tests/test_evoked_difference.py
meggie_difference/actions/spectrum_difference/__init__.py
meggie_difference/actions/spectrum_difference/configuration.json
meggie_difference/actions/spectrum_difference/tests/__init__.py
meggie_difference/actions/spectrum_difference/tests/test_spectrum_difference.py
meggie_difference/actions/tfr_difference/__init__.py
meggie_difference/actions/tfr_difference/configuration.json
meggie_difference/actions/tfr_difference/tests/__init__.py
meggie_difference/actions/tfr_difference/tests/test_tfr_difference.py
meggie_difference/utilities/__init__.py
meggie_difference/utilities/dialogs/differenceDialogMain.py
meggie_difference/utilities/dialogs/differenceDialogUi.py
meggie_difference/utilities/dialogs/differenceDialogUi.ui
meggie_difference-0.2.0.dist-info/METADATA
meggie_difference-0.2.0.dist-info/WHEEL
meggie_difference-0.2.0.dist-info/top_level.txt
meggie_difference-0.2.0.dist-info/RECORD
